elegance_spider/__init__.py
elegance_spider/item.py
elegance_spider/redis_hash.py
elegance_spider/set.py
elegance_spider/async/__init__.py
elegance_spider/conf/__init__.py
elegance_spider/conf/default_settings.py
elegance_spider/conf/settings.py
elegance_spider/core/__init__.py
elegance_spider/core/downloader.py
elegance_spider/core/engine.py
elegance_spider/core/pipeline.py
elegance_spider/core/scheduler.py
elegance_spider/core/spider.py
elegance_spider/http/__init__.py
elegance_spider/http/request.py
elegance_spider/http/response.py
elegance_spider/middleware/__init__.py
elegance_spider/middleware/downloader_middleware.py
elegance_spider/middleware/spider_middleware.py
elegance_spider/utils/__init__.py
elegance_spider/utils/coroutine.py
elegance_spider/utils/log.py
elegance_spider/utils/queue.py
elegance_spider/utils/stats_collector.py
elegance_spider-0.0.3.dist-info/METADATA
elegance_spider-0.0.3.dist-info/WHEEL
elegance_spider-0.0.3.dist-info/top_level.txt
elegance_spider-0.0.3.dist-info/RECORD
